vit_b16_keras/__init__.py
vit_b16_keras/vit_b16.py
vit_b16_keras-0.5.dist-info/License.txt
vit_b16_keras-0.5.dist-info/METADATA
vit_b16_keras-0.5.dist-info/WHEEL
vit_b16_keras-0.5.dist-info/top_level.txt
vit_b16_keras-0.5.dist-info/RECORD
