Metadata-Version: 2.1
Name: vit-b16-keras
Version: 0.5
Summary: vit-b16-keras
Home-page: UNKNOWN
Author: Elena Paul
Author-email: wohani7266@dotvilla.com
License: UNKNOWN
Keywords: arithmetic,math,mathematics
Platform: UNKNOWN
Classifier: Development Status :: 1 - Planning
Classifier: Intended Audience :: Developers
Classifier: Programming Language :: Python :: 3
Classifier: Operating System :: Unix
Classifier: Operating System :: MacOS :: MacOS X
Classifier: Operating System :: Microsoft :: Windows
Requires-Dist: tensorflow
